textg2p/__init__.py
textg2p/transcriber.py
textg2p-0.1.5.dist-info/LICENSE
textg2p-0.1.5.dist-info/METADATA
textg2p-0.1.5.dist-info/WHEEL
textg2p-0.1.5.dist-info/top_level.txt
textg2p-0.1.5.dist-info/RECORD
