Metadata-Version: 2.1
Name: textg2p
Version: 0.1.5
Summary: A package to transform texts to ipa
Home-page: https://github.com/intexcor/textg2p
Author: Ivan Shivalov
Author-email: ivansivalov396@gmail.com
Classifier: Programming Language :: Python
Classifier: License :: OSI Approved :: GNU General Public License v3 (GPLv3)
License-File: LICENSE
Requires-Dist: eng-to-ipa
Requires-Dist: epitran
Requires-Dist: jamo
Requires-Dist: g2pk
Requires-Dist: lingua-language-detector
